pyvqnet/__init__.py
pyvqnet/__init__.pyi
pyvqnet/_core.pyd
pyvqnet/backends.cp310-win_amd64.pyd
pyvqnet/backends.pyi
pyvqnet/backends_mock.cp310-win_amd64.pyd
pyvqnet/backends_mock.pyi
pyvqnet/config.cp310-win_amd64.pyd
pyvqnet/config.pyi
pyvqnet/device.cp310-win_amd64.pyd
pyvqnet/device.pyi
pyvqnet/dtype.cp310-win_amd64.pyd
pyvqnet/dtype.pyi
pyvqnet/logger.cp310-win_amd64.pyd
pyvqnet/logger.pyi
pyvqnet/summary.cp310-win_amd64.pyd
pyvqnet/summary.pyi
pyvqnet/types.cp310-win_amd64.pyd
pyvqnet/types.pyi
pyvqnet/version.cp310-win_amd64.pyd
pyvqnet/version.pyi
pyvqnet/data/__init__.py
pyvqnet/data/__init__.pyi
pyvqnet/data/collate.cp310-win_amd64.pyd
pyvqnet/data/collate.pyi
pyvqnet/data/data.cp310-win_amd64.pyd
pyvqnet/data/data.pyi
pyvqnet/data/dataloader.cp310-win_amd64.pyd
pyvqnet/data/dataloader.pyi
pyvqnet/data/fetch.cp310-win_amd64.pyd
pyvqnet/data/fetch.pyi
pyvqnet/data/sampler.cp310-win_amd64.pyd
pyvqnet/data/sampler.pyi
pyvqnet/data/signal_handling.cp310-win_amd64.pyd
pyvqnet/data/signal_handling.pyi
pyvqnet/data/transform.cp310-win_amd64.pyd
pyvqnet/data/transform.pyi
pyvqnet/data/utils.cp310-win_amd64.pyd
pyvqnet/data/utils.pyi
pyvqnet/data/worker.cp310-win_amd64.pyd
pyvqnet/data/worker.pyi
pyvqnet/distributed/ControlComm.cp310-win_amd64.pyd
pyvqnet/distributed/ControlComm.pyi
pyvqnet/distributed/__init__.py
pyvqnet/distributed/__init__.pyi
pyvqnet/distributed/check_mpi_available.cp310-win_amd64.pyd
pyvqnet/distributed/check_mpi_available.pyi
pyvqnet/distributed/datasplit.cp310-win_amd64.pyd
pyvqnet/distributed/datasplit.pyi
pyvqnet/distributed/distributed_sampler.cp310-win_amd64.pyd
pyvqnet/distributed/distributed_sampler.pyi
pyvqnet/distributed/gradient_allreduce.cp310-win_amd64.pyd
pyvqnet/distributed/gradient_allreduce.pyi
pyvqnet/distributed/configs/__init__.pyi
pyvqnet/distributed/configs/comm.cp310-win_amd64.pyd
pyvqnet/distributed/configs/comm.pyi
pyvqnet/distributed/configs/constants.cp310-win_amd64.pyd
pyvqnet/distributed/configs/constants.pyi
pyvqnet-2.17.2.dist-info/licenses/LICENSE
pyvqnet-2.17.2.dist-info/METADATA
pyvqnet-2.17.2.dist-info/WHEEL
pyvqnet-2.17.2.dist-info/top_level.txt
pyvqnet-2.17.2.dist-info/RECORD
