Metadata-Version: 2.4
Name: pyvqnet
Version: 2.17.2
Summary: A quantum machine learning framework designed for unified development of both classical and quantum machine learning tasks.
Author: OriginQ
License-File: LICENSE
Requires-Dist: setuptools
Requires-Dist: numpy<2.0,>=1.18.5
Requires-Dist: joblib>=1.1.0
Requires-Dist: pyqpanda3
Requires-Dist: scipy>=1.9.3
Requires-Dist: rustworkx>=0.13.2
Requires-Dist: Pillow>=10.2.0
Requires-Dist: hjson
Requires-Dist: Cython>=3.0.0
Requires-Dist: packaging
Requires-Dist: nvidia-cublas-cu11==11.11.3.6
Requires-Dist: nvidia-cuda-runtime-cu11==11.8.89
Requires-Dist: nvidia-cuda-cupti-cu11==11.8.87
Requires-Dist: nvidia-cuda-nvrtc-cu11==11.8.89
Requires-Dist: nvidia-cufft-cu11==10.9.0.58
Requires-Dist: nvidia-cusolver-cu11==11.4.1.48
Requires-Dist: nvidia-cusparse-cu11==11.7.5.86
Requires-Dist: nvidia-nvtx-cu11==11.8.86
Requires-Dist: nvidia-curand-cu11==10.3.0.86
Dynamic: author
Dynamic: license-file
Dynamic: requires-dist
Dynamic: summary
